report_analysis/__init__.py
report_analysis/analyzer.py
ReportAnalysis-0.2.dist-info/LICENSE
ReportAnalysis-0.2.dist-info/METADATA
ReportAnalysis-0.2.dist-info/WHEEL
ReportAnalysis-0.2.dist-info/entry_points.txt
ReportAnalysis-0.2.dist-info/top_level.txt
ReportAnalysis-0.2.dist-info/RECORD
